LICENSE
MANIFEST.in
README.rst
setup.cfg
setup.py
HDDM.egg-info/PKG-INFO
HDDM.egg-info/SOURCES.txt
HDDM.egg-info/dependency_links.txt
HDDM.egg-info/requires.txt
HDDM.egg-info/top_level.txt
docs/graveyard/abstract.rst
docs/graveyard/conclusions.rst
docs/graveyard/demo_gonogo.rst
docs/graveyard/demos.rst
docs/graveyard/tutorial_python.rst
docs/source/demo_HDDMnnRL.rst
docs/source/demo_RLHDDMtutorial.rst
docs/source/hddm.models.rst
docs/source/hddm.rst
docs/source/hddm.simulators.rst
docs/source/hddm.torch.rst
docs/source/howto.rst
docs/source/index.rst
docs/source/intro.rst
docs/source/lan_add_custom_lans.rst
docs/source/lan_extension.rst
docs/source/lan_investigate_model_behavior.rst
docs/source/lan_network_inspectors.rst
docs/source/lan_new_classes.rst
docs/source/lan_new_models.rst
docs/source/lan_to_hddm_end_to_end.rst
docs/source/lan_tutorial.rst
docs/source/lan_visualizations.rst
docs/source/methods.rst
docs/source/mnle_to_hddm_end_to_end.rst
docs/source/modules.rst
docs/source/references.rst
docs/source/tutorial_basic_hddm.rst
docs/source/tutorial_gonogo_chisquare.rst
docs/source/tutorial_model_plot.rst
docs/source/tutorial_post_pred.rst
docs/source/tutorial_regression_stimcoding.rst
docs/source/tutorial_set_parameter_defaults.rst
docs/source/tutorials.rst
hddm/MPLTraits.py
hddm/MPLTraits_qt.py
hddm/__init__.py
hddm/diag.py
hddm/generate.py
hddm/likelihoods.py
hddm/likelihoods_mlp.py
hddm/model_config.py
hddm/model_config_rl.py
hddm/network_inspectors.py
hddm/plotting.py
hddm/plotting_old.py
hddm/utils.py
hddm/examples/__init__.py
hddm/examples/cavanagh_theta_nn.csv
hddm/examples/plot_posterior_quantiles.py
hddm/examples/rlddm_data.csv
hddm/examples/simple_difficulty.conf
hddm/examples/simple_difficulty.csv
hddm/examples/simple_model.py
hddm/examples/simple_subjs_difficulty.csv
hddm/examples/simple_subjs_difficulty_single.csv
hddm/examples/demo_HDDMnnRL/rlssm_data.csv
hddm/examples/demo_HDDMnnRL/rlssm_reg_data.csv
hddm/examples/demo_HDDMnnRL/demo_HDDMnnRL_files/demo_HDDMnnRL_12_1.png
hddm/examples/demo_HDDMnnRL/demo_HDDMnnRL_files/demo_HDDMnnRL_12_10.png
